.coveragerc
.gitignore
.travis.yml
CHANGES.txt
CONTRIBUTORS.txt
MANIFEST.in
README.rst
base.cfg
bootstrap.py
buildout.cfg
setup.py
travis.cfg
collective/__init__.py
collective.favoriting.egg-info/PKG-INFO
collective.favoriting.egg-info/SOURCES.txt
collective.favoriting.egg-info/dependency_links.txt
collective.favoriting.egg-info/entry_points.txt
collective.favoriting.egg-info/namespace_packages.txt
collective.favoriting.egg-info/not-zip-safe
collective.favoriting.egg-info/requires.txt
collective.favoriting.egg-info/top_level.txt
collective/favoriting/__init__.py
collective/favoriting/configure.zcml
collective/favoriting/layer.py
collective/favoriting/permissions.py
collective/favoriting/permissions.zcml
collective/favoriting/storage.py
collective/favoriting/testing.py
collective/favoriting/upgrades.py
collective/favoriting/upgrades.zcml
collective/favoriting/browser/__init__.py
collective/favoriting/browser/configure.zcml
collective/favoriting/browser/favoriting_view.pt
collective/favoriting/browser/favoriting_view.py
collective/favoriting/locales/collective.favoriting.pot
collective/favoriting/locales/en/LC_MESSAGES/collective.favoriting.mo
collective/favoriting/locales/en/LC_MESSAGES/collective.favoriting.po
collective/favoriting/locales/fr/LC_MESSAGES/collective.favoriting.mo
collective/favoriting/locales/fr/LC_MESSAGES/collective.favoriting.po
collective/favoriting/profiles/default/actions.xml
collective/favoriting/profiles/default/browserlayer.xml
collective/favoriting/profiles/default/catalog.xml
collective/favoriting/profiles/default/metadata.xml
collective/favoriting/tests/__init__.py
collective/favoriting/tests/base.py
collective/favoriting/tests/test_robot.py
collective/favoriting/tests/test_setup.py
collective/favoriting/tests/test_storage.py
collective/favoriting/tests/test_views.py
docs/LICENSE.txt